{
  "artifact_id": "fd6c7486-4153-4d49-849d-dd2945f2ef08",
  "title": "Zhihu Hot List",
  "data": [
    {
      "rank": "1",
      "title": "中美元首于 6 月 5 日晚通电话，释放了哪些信号？",
      "link": "https://www.zhihu.com/question/1914063681551070993",
      "heat": "860 万热度"
    },
    {
      "rank": "2",
      "title": "6 月 5 日，世界杯亚洲区预选赛，国足客场 0-1 负于印尼，世界杯希望破灭，如何评价本场比赛？",
      "link": "https://www.zhihu.com/question/1913303832399713557",
      "heat": "576 万热度"
    },
    {
      "rank": "3",
      "title": "东风与长安重组终止，长安汽车将升级为独立央企，这一变革对企业及汽车行业分别会带来哪些影响？",
      "link": "https://www.zhihu.com/question/1913885494447677612",
      "heat": "308 万热度"
    },
    {
      "rank": "4",
      "title": "花旗银行启动大规模裁员，减少约 3500 名技术人员，赔偿 N+6，如何评价？",
      "link": "https://www.zhihu.com/question/1913930722370103053",
      "heat": "262 万热度"
    },
    {
      "rank": "5",
      "title": "三亚女游客死亡记录公布「曾诊断为不明生物咬伤，治疗中注射了蛇毒血清」，怎样解读？诊断及治疗方法准确吗？",
      "link": "https://www.zhihu.com/question/1914025343502742299",
      "heat": "183 万热度"
    },
    {
      "rank": "6",
      "title": "博主称一辆东风风行雷霆 630 Pro 跑了 31 万公里后电池被锁，具体情况如何？厂家这么做合规吗？",
      "link": "https://www.zhihu.com/question/1912197269001839876",
      "heat": "173 万热度"
    },
    {
      "rank": "7",
      "title": "特朗普全面暂停 12 个国家的公民进入美国，为何是这些国家？对美国有哪些影响？",
      "link": "https://www.zhihu.com/question/1913869817540207394",
      "heat": "170 万热度"
    },
    {
      "rank": "8",
      "title": "西安上空现大量白点状不明飞行物，目击者称感觉比飞机高，可能是什么？",
      "link": "https://www.zhihu.com/question/1914020692443226660",
      "heat": "168 万热度"
    },
    {
      "rank": "9",
      "title": "根据美国卫星图像显示，朝鲜受损的崔贤级驱逐舰已经被扶正，这背后的技术支持和资源投入意味着什么？",
      "link": "https://www.zhihu.com/question/1913616294210667983",
      "heat": "152 万热度"
    },
    {
      "rank": "10",
      "title": "女子姓名与被执行人同音多次遭传唤，澄清后仍有执行人员到单位调查，法院为何会反复找错人？反映出哪些问题？",
      "link": "https://www.zhihu.com/question/1913553993889703065",
      "heat": "133 万热度"
    },
    {
      "rank": "11",
      "title": "美国企业能找到破解稀土的难题吗？",
      "link": "https://www.zhihu.com/question/1913685897372730507",
      "heat": "121 万热度"
    },
    {
      "rank": "12",
      "title": "现在动不动就说某某演员演技封神，封神究竟是个什么水平？",
      "link": "https://www.zhihu.com/question/650447383",
      "heat": "106 万热度"
    },
    {
      "rank": "13",
      "title": "如何看待公安机关首次通过执法行动对「台独」分裂势力亮剑，广州警方悬赏通缉 20 名台湾「资通电军」？",
      "link": "https://www.zhihu.com/question/1913876933487363143",
      "heat": "94 万热度"
    },
    {
      "rank": "14",
      "title": "国足无缘 2026 世界杯，主教练伊万该下课吗？假如伊万下课，你看好谁来接任？",
      "link": "https://www.zhihu.com/question/1914109109394956715",
      "heat": "88 万热度"
    },
    {
      "rank": "15",
      "title": "手动挡，你们是一档一档往上加，还是从一档直接到三档再往上？",
      "link": "https://www.zhihu.com/question/652616004",
      "heat": "87 万热度"
    },
    {
      "rank": "16",
      "title": "如何评价周杰伦 2025 年 06 月 06 日发布的新单曲《即兴曲》？",
      "link": "https://www.zhihu.com/question/1914042860682061009",
      "heat": "85 万热度"
    },
    {
      "rank": "17",
      "title": "国足提前 1 轮无缘 2026 美加墨世界杯，如何评价国足整个 18 强赛的表现？哪场比赛最可惜？",
      "link": "https://www.zhihu.com/question/1914108661304881561",
      "heat": "84 万热度"
    },
    {
      "rank": "18",
      "title": "如何看待雷军称小米 YU7 定价不会是 23.59 万，还说汽车业务今年内盈利？",
      "link": "https://www.zhihu.com/question/1913337715186995734",
      "heat": "82 万热度"
    },
    {
      "rank": "19",
      "title": "聪明是一种什么感觉？",
      "link": "https://www.zhihu.com/question/24103735",
      "heat": "71 万热度"
    },
    {
      "rank": "20",
      "title": "《记承天寺夜游》中苏轼为何知道张怀民没有休息？",
      "link": "https://www.zhihu.com/question/6755360845",
      "heat": "69 万热度"
    },
    {
      "rank": "21",
      "title": "你看到的关于「苏超」最有意思的梗是什么？为什么大家热衷于给「苏超」造梗？",
      "link": "https://www.zhihu.com/question/1913667750250902775",
      "heat": "69 万热度"
    },
    {
      "rank": "22",
      "title": "背完 3500 词，英语就能考到 130 吗？",
      "link": "https://www.zhihu.com/question/656548145",
      "heat": "67 万热度"
    },
    {
      "rank": "23",
      "title": "全国护眼日到了，说说你做过最正确的护眼投资是什么？",
      "link": "https://www.zhihu.com/question/1911002373444342779",
      "heat": "62 万热度"
    },
    {
      "rank": "24",
      "title": "发明魔芋的前辈是经历了什么?",
      "link": "https://www.zhihu.com/question/596712008",
      "heat": "59 万热度"
    },
    {
      "rank": "25",
      "title": "当我们做二次量子化的时候，我们究竟在做什么？",
      "link": "https://www.zhihu.com/question/302491973",
      "heat": "59 万热度"
    },
    {
      "rank": "26",
      "title": "郭靖，许三多，阿甘本质上是不是同一类人？",
      "link": "https://www.zhihu.com/question/7931124897",
      "heat": "59 万热度"
    },
    {
      "rank": "27",
      "title": "养猫之后，你的底线降到哪一步了？",
      "link": "https://www.zhihu.com/question/1909335025738023183",
      "heat": "58 万热度"
    },
    {
      "rank": "28",
      "title": "《王者荣耀》射手鲁班七号为什么是最容易挨抓的？",
      "link": "https://www.zhihu.com/question/1912459261348386261",
      "heat": "56 万热度"
    },
    {
      "rank": "29",
      "title": "商务部回应汽车行业「内卷式」竞争，将积极配合相关部门加强综合整治与合规引导，目前车企竞争存在哪些问题？",
      "link": "https://www.zhihu.com/question/1913984784432084203",
      "heat": "54 万热度"
    },
    {
      "rank": "30",
      "title": "为什么西安适合建都？",
      "link": "https://www.zhihu.com/question/666184557",
      "heat": "54 万热度"
    },
    {
      "rank": "31",
      "title": "领导把你当成「棋子」一直在利用你，你能接受吗？",
      "link": "https://www.zhihu.com/question/3054341577",
      "heat": "53 万热度"
    },
    {
      "rank": "32",
      "title": "20 名台湾民进党当局「资通电军」首要嫌犯曝光，广州警方悬赏通缉，有哪些信息值得关注？",
      "link": "https://www.zhihu.com/question/1913876932325533155",
      "heat": "53 万热度"
    },
    {
      "rank": "33",
      "title": "LPL 2025 赛季第二赛段淘汰赛 WE 3:1 JDG，如何评价这场比赛？",
      "link": "https://www.zhihu.com/question/1913989556493072092",
      "heat": "51 万热度"
    },
    {
      "rank": "34",
      "title": "这么多编程语言，有没有一种可能能把他们「大一统」？",
      "link": "https://www.zhihu.com/question/14502504808",
      "heat": "50 万热度"
    },
    {
      "rank": "35",
      "title": "中国和日本的街景都有哪些差异？能否举几个例子说明？",
      "link": "https://www.zhihu.com/question/473244368",
      "heat": "50 万热度"
    },
    {
      "rank": "36",
      "title": "你坚持使用美团外卖的理由是什么 ？",
      "link": "https://www.zhihu.com/question/1913642684234573323",
      "heat": "50 万热度"
    },
    {
      "rank": "37",
      "title": "科学家发现一颗超级地球 Kepler-725c，可能存在类地生命，什么是超级地球？能适合人类生存吗？",
      "link": "https://www.zhihu.com/question/1913368137421775878",
      "heat": "50 万热度"
    },
    {
      "rank": "38",
      "title": "如何看待小米 15S Pro 的首发销量，是否达到小米的预期？",
      "link": "https://www.zhihu.com/question/1913348049624883907",
      "heat": "49 万热度"
    },
    {
      "rank": "39",
      "title": "如何看待尊界 S800 超豪华内饰及引领时代的顶尖科技实力？有哪些亮点值得关注？",
      "link": "https://www.zhihu.com/question/1911773558339768713",
      "heat": "49 万热度"
    },
    {
      "rank": "40",
      "title": "为什么有些门开关时特别容易夹手？背后的设计缺陷可能有哪些？",
      "link": "https://www.zhihu.com/question/1913549009143967994",
      "heat": "49 万热度"
    },
    {
      "rank": "41",
      "title": "如果有一款架空世界观游戏，人类从未点亮火药这一科技，我们该如何设计远程武器科技树？",
      "link": "https://www.zhihu.com/question/1911803440738317986",
      "heat": "49 万热度"
    },
    {
      "rank": "42",
      "title": "白象多半袋面的「多半」是商标，这种行为是否涉及虚假宣传？消费者如何应对商标套路？",
      "link": "https://www.zhihu.com/question/1913626861910582406",
      "heat": "49 万热度"
    },
    {
      "rank": "43",
      "title": "为什么小时候看容嬷嬷扎针只觉得她很坏，现在却有些共情甚至理解她？",
      "link": "https://www.zhihu.com/question/1911855901226297324",
      "heat": "49 万热度"
    },
    {
      "rank": "44",
      "title": "偶尔也想得到孩子的理解，怎么和孩子沟通这个问题？",
      "link": "https://www.zhihu.com/question/1913289568695853612",
      "heat": "49 万热度"
    },
    {
      "rank": "45",
      "title": "假设现在高考题目出错，到底是全部给分更公平，还是全部不得分更公平？",
      "link": "https://www.zhihu.com/question/1907194403442886335",
      "heat": "49 万热度"
    },
    {
      "rank": "46",
      "title": "什么是稳定币？有人说它是「一场饮鸩止渴的游戏」，你怎么看？",
      "link": "https://www.zhihu.com/question/1913167364486291776",
      "heat": "49 万热度"
    },
    {
      "rank": "47",
      "title": "本科阶段，文史哲真的没有专业壁垒吗？",
      "link": "https://www.zhihu.com/question/1912872468361750040",
      "heat": "49 万热度"
    },
    {
      "rank": "48",
      "title": "假如做家务是一场链式反应，哪一环最易触发你的情绪临界点？",
      "link": "https://www.zhihu.com/question/1913671753068155247",
      "heat": "49 万热度"
    },
    {
      "rank": "49",
      "title": "孩子数学考试考了 6 分，怎么去和她沟通?",
      "link": "https://www.zhihu.com/question/1898627183213277239",
      "heat": "49 万热度"
    },
    {
      "rank": "50",
      "title": "49 岁的小因扎吉即将告别国米并出任利雅得新月主帅，他的职业生涯要迎来新的挑战和机遇了吗？",
      "link": "https://www.zhihu.com/question/1913193379761755134",
      "heat": "49 万热度"
    }
  ],
  "generated_at": "2025-06-06 02:56:59"
}