{
  "artifact_id": "a8078845-9135-4a80-987b-4f3b6669ab71",
  "title": "Zhihu Hot List",
  "data": [
    {
      "rank": "1",
      "title": "小米 YU7 交付周期长，蔚来极氪等多家车企愿为退订用户补定金，怎样看这一做法？小米能缩短交付周期吗？",
      "link": "https://www.zhihu.com/question/1923114337490400493",
      "heat": "569 万热度"
    },
    {
      "rank": "2",
      "title": "如何看待波尔邀请樊振东参加退役仪式，双方发文互送祝福？你有什么感悟吗？",
      "link": "https://www.zhihu.com/question/1922731485208777084",
      "heat": "414 万热度"
    },
    {
      "rank": "3",
      "title": "沙漠对于人类来说不是很有用，但从地球的角度看是不是也是地球自己的需要？",
      "link": "https://www.zhihu.com/question/661994985",
      "heat": "300 万热度"
    },
    {
      "rank": "4",
      "title": "多名公职人员因微信办公违规被处理，使用微信办公存在哪些隐患？普通人使用微信还能保障隐私安全吗？",
      "link": "https://www.zhihu.com/question/1923299111429437227",
      "heat": "290 万热度"
    },
    {
      "rank": "5",
      "title": "如何看待苏超联赛第五轮场均现场观众突破 3 万大关？",
      "link": "https://www.zhihu.com/question/1922780719572325173",
      "heat": "239 万热度"
    },
    {
      "rank": "6",
      "title": "人类文明有没有可能一直延续到太阳变成红巨星的时候?",
      "link": "https://www.zhihu.com/question/7351358585",
      "heat": "208 万热度"
    },
    {
      "rank": "7",
      "title": "中国小猫意外运到美国，在无食无水的情况下生存了三周，为什么猫的生存能力这么强？",
      "link": "https://www.zhihu.com/question/1919749575972972212",
      "heat": "174 万热度"
    },
    {
      "rank": "8",
      "title": "马斯克脑机接口公司称计划最快明年让盲人复明，请问脑机接口行业的经济前景有多广阔，会淘汰哪些行业？",
      "link": "https://www.zhihu.com/question/1922928357403780721",
      "heat": "149 万热度"
    },
    {
      "rank": "9",
      "title": "我要为了偏远 985 放弃去上好地区的 211 吗?",
      "link": "https://www.zhihu.com/question/1922386115479962816",
      "heat": "144 万热度"
    },
    {
      "rank": "10",
      "title": "韩雪被指文物前使用强光拍摄，景区回应是在录节目，使用的并非强光灯，强光与闪光灯会对文物造成哪些损伤？",
      "link": "https://www.zhihu.com/question/1921619226218685110",
      "heat": "139 万热度"
    },
    {
      "rank": "11",
      "title": "百度开源了文心一言 ERNIE 4.5 模型，这对国内大模型生态意味着什么？",
      "link": "https://www.zhihu.com/question/1922960278926128005",
      "heat": "131 万热度"
    },
    {
      "rank": "12",
      "title": "大家觉得洪宇宙演的周瑜怎么样?",
      "link": "https://www.zhihu.com/question/549872262",
      "heat": "126 万热度"
    },
    {
      "rank": "13",
      "title": "2025 上半年总票房 292.31 亿，《哪吒 2》票房占比 52.8%，如何看待这一数据？",
      "link": "https://www.zhihu.com/question/1923126738738741263",
      "heat": "123 万热度"
    },
    {
      "rank": "14",
      "title": "如何看 2025Msi 正赛时间，BLG 被安排在国内时间凌晨三点？",
      "link": "https://www.zhihu.com/question/1923064463587778986",
      "heat": "122 万热度"
    },
    {
      "rank": "15",
      "title": "汤姆·克鲁斯获奥斯卡终身成就奖，获得影艺生涯首座小金人，他的哪些作品和特技表现最能体现这一荣誉？",
      "link": "https://www.zhihu.com/question/1918663748991813365",
      "heat": "115 万热度"
    },
    {
      "rank": "16",
      "title": "如何看待网传韦东奕转升长聘副教授申请已经公示？此事若属实，其从助理教授晋升意味着什么？",
      "link": "https://www.zhihu.com/question/1922959459103236160",
      "heat": "112 万热度"
    },
    {
      "rank": "17",
      "title": "为什么现代父母越来越重视「高质量陪伴」，却依然难以摆脱「隐性失陪」的困境？",
      "link": "https://www.zhihu.com/question/1921490533886436224",
      "heat": "110 万热度"
    },
    {
      "rank": "18",
      "title": "看完陈思诚新片《恶意》你有什么感受？有哪些不易察觉的细节？",
      "link": "https://www.zhihu.com/question/1922657877404936011",
      "heat": "106 万热度"
    },
    {
      "rank": "19",
      "title": "掘金送走小波特与 2032 年首轮，换回卡梅伦 - 约翰逊，同时签回布鲁斯 - 布朗，如何看待掘金的操作？",
      "link": "https://www.zhihu.com/question/1923321647928143905",
      "heat": "104 万热度"
    },
    {
      "rank": "20",
      "title": "世俱杯 1/8 决赛爆大冷门，曼城 3-4 利雅得新月，如何评价本场比赛？",
      "link": "https://www.zhihu.com/question/1923089469172574051",
      "heat": "103 万热度"
    },
    {
      "rank": "21",
      "title": "男子在地铁中穿病号服拍摄引发乘客恐慌，已被行政处罚，怎样看待他们的行为？如何从法律角度解读？",
      "link": "https://www.zhihu.com/question/1923068589256172212",
      "heat": "100 万热度"
    },
    {
      "rank": "22",
      "title": "1-6 月全国房产销售额下跌 11.8%，呈现一线土拍溢价上涨和销售持续下滑共存现象，对此你怎么看？",
      "link": "https://www.zhihu.com/question/1923294376454516859",
      "heat": "85 万热度"
    },
    {
      "rank": "23",
      "title": "中国为何不是很流行太阳神崇拜？",
      "link": "https://www.zhihu.com/question/1904884528989835987",
      "heat": "83 万热度"
    },
    {
      "rank": "24",
      "title": "如何评价杨紫、李现主演的电视剧《锦绣芳华》？",
      "link": "https://www.zhihu.com/question/1922045516432278603",
      "heat": "66 万热度"
    },
    {
      "rank": "25",
      "title": "如果把焦虑看作大脑的「过度保护机制」，我们应该如何与它和解？",
      "link": "https://www.zhihu.com/question/1921345488168420129",
      "heat": "66 万热度"
    },
    {
      "rank": "26",
      "title": "河南女子购买新房装修时挖出人骨，警方称人骨年代久远应为男性，这种情况房主能要求退房、换房吗？",
      "link": "https://www.zhihu.com/question/1923043915600204321",
      "heat": "64 万热度"
    },
    {
      "rank": "27",
      "title": "自我厌恶的根源，究竟是对现实自我的不满？还是对理想化自我的过度执念？",
      "link": "https://www.zhihu.com/question/1921248497249814124",
      "heat": "62 万热度"
    },
    {
      "rank": "28",
      "title": "美国政府欲重夺全球核能领导地位，通过多项行政令促核电发展，如何看待此举？美国核能产业现状如何？",
      "link": "https://www.zhihu.com/question/1921259494341571347",
      "heat": "59 万热度"
    },
    {
      "rank": "29",
      "title": "《战锤 40k》系列可能的结局是什么？",
      "link": "https://www.zhihu.com/question/348894270",
      "heat": "58 万热度"
    },
    {
      "rank": "30",
      "title": "都是刘和平编剧，为什么《雍正王朝》当年收视爆火而《大明王朝 1566》却遇冷直到十年后才小范围火起来？",
      "link": "https://www.zhihu.com/question/478233531",
      "heat": "57 万热度"
    },
    {
      "rank": "31",
      "title": "舞蹈培训市场乱象遭曝光，涉无资质办学、师资证书造假等，家长该如何辨别？出问题后该如何维权？",
      "link": "https://www.zhihu.com/question/1922923921365234067",
      "heat": "57 万热度"
    },
    {
      "rank": "32",
      "title": "阿森纳为什么很难夺冠？",
      "link": "https://www.zhihu.com/question/1921782300204599193",
      "heat": "56 万热度"
    },
    {
      "rank": "33",
      "title": "美国 GBU-57 钻地弹是靠什么力钻那么深？",
      "link": "https://www.zhihu.com/question/1921615460669064958",
      "heat": "56 万热度"
    },
    {
      "rank": "34",
      "title": "A 股上半年收官，沪指涨 2.76%，北证 50 大涨近 40%，近二十只银行股创新高，后市怎么走？",
      "link": "https://www.zhihu.com/question/1923051479276683730",
      "heat": "56 万热度"
    },
    {
      "rank": "35",
      "title": "容声冰箱为什么能让《长安的荔枝》放弃其他冰箱大牌？",
      "link": "https://www.zhihu.com/question/1921887169842251082",
      "heat": "56 万热度"
    },
    {
      "rank": "36",
      "title": "昆仑山采药刻石，为什么会突然引起这么大争议?",
      "link": "https://www.zhihu.com/question/1919649686668686710",
      "heat": "55 万热度"
    },
    {
      "rank": "37",
      "title": "如果你孩子跟你说，他长大了要挣很多钱，还要跟你买大别墅，请保姆，你该怎样告诉他，钱没有你想象的好挣？",
      "link": "https://www.zhihu.com/question/1909524546991682068",
      "heat": "55 万热度"
    },
    {
      "rank": "38",
      "title": "物业撤走了，没有业主委员会，小区要怎么管理？",
      "link": "https://www.zhihu.com/question/616391918",
      "heat": "55 万热度"
    },
    {
      "rank": "39",
      "title": "为什么熬夜晚起不健康，早睡早起就健康？",
      "link": "https://www.zhihu.com/question/30523587",
      "heat": "55 万热度"
    },
    {
      "rank": "40",
      "title": "多机场禁止携带罗马仕、安克等品牌召回型号及批次充电宝，那这些品牌不在召回名单中的充电宝还能放心用吗？",
      "link": "https://www.zhihu.com/question/1921217344979558501",
      "heat": "55 万热度"
    },
    {
      "rank": "41",
      "title": "程序员的代码为什么不写注释？",
      "link": "https://www.zhihu.com/question/1916830550880139152",
      "heat": "55 万热度"
    },
    {
      "rank": "42",
      "title": "茅台 1935 在「2025 中国影视之夜」的哪些细节，体现了对影视作品与东方文化的致敬？",
      "link": "https://www.zhihu.com/question/1921892961119076668",
      "heat": "53 万热度"
    },
    {
      "rank": "43",
      "title": "为什么感觉现在 switch 不如小时候 gba 好玩？",
      "link": "https://www.zhihu.com/question/1922587108587082941",
      "heat": "52 万热度"
    },
    {
      "rank": "44",
      "title": "为什么宠物狗可以天天自己溜自己，宠物猫走丢后却很难自己找回家呢？",
      "link": "https://www.zhihu.com/question/1889391754484106332",
      "heat": "52 万热度"
    },
    {
      "rank": "45",
      "title": "小岛秀夫是「游戏电影化」的忠实布道者，你觉得游戏继续走这条路是对的吗？",
      "link": "https://www.zhihu.com/question/1921284299115717150",
      "heat": "52 万热度"
    },
    {
      "rank": "46",
      "title": "30 年过去了，美国没有比 B2 更强的轰炸机了么？",
      "link": "https://www.zhihu.com/question/1920520178900402364",
      "heat": "51 万热度"
    },
    {
      "rank": "47",
      "title": "500 元档白酒里，是否真的存在口感和品质都接近千元档的白酒？",
      "link": "https://www.zhihu.com/question/1921566090301010785",
      "heat": "50 万热度"
    },
    {
      "rank": "48",
      "title": "为什么有的程序员很抗拒使用 Ai?",
      "link": "https://www.zhihu.com/question/1919478868361842758",
      "heat": "49 万热度"
    },
    {
      "rank": "49",
      "title": "同事间的「奶茶社交」到底弊大于利还是利大于弊？作为职场新人，该如何应对这种社交方式？",
      "link": "https://www.zhihu.com/question/1921575562893304107",
      "heat": "49 万热度"
    },
    {
      "rank": "50",
      "title": "怎么才能克服和人说话时的「讨好感」？",
      "link": "https://www.zhihu.com/question/1920796983846741861",
      "heat": "49 万热度"
    }
  ],
  "generated_at": "2025-07-01 13:40:47"
}