{
  "artifact_id": "9d3096ca-7772-440d-972e-5c44177808f2",
  "title": "Zhihu Hot List",
  "data": [
    {
      "rank": "1",
      "title": "8 月 22 日沪指突破 3800 点，续创 10 年新高，芯片产业链领涨，如何看待 A 股后续走势？",
      "link": "https://www.zhihu.com/question/1942152568387110509",
      "heat": "644 万热度"
    },
    {
      "rank": "2",
      "title": "新加坡三名小学生霸凌同学被停课，一人被执行鞭刑，如何看待这一处罚措施？新加坡惩戒霸凌哪些经验可借鉴？",
      "link": "https://www.zhihu.com/question/1942183864823932379",
      "heat": "361 万热度"
    },
    {
      "rank": "3",
      "title": "河南「中式迪士尼」暑假客流激增，每日入园人次超五六万，成为少数盈利的主题景区，它日进斗金的秘诀是什么？",
      "link": "https://www.zhihu.com/question/1941132182069450706",
      "heat": "223 万热度"
    },
    {
      "rank": "4",
      "title": "网友质疑无座与二等座票价相同是否合理，12306 称「无座可暂时坐空余座位，合理定价」，你认同吗？",
      "link": "https://www.zhihu.com/question/1942133062323365043",
      "heat": "137 万热度"
    },
    {
      "rank": "5",
      "title": "如何看待寒武纪目前市值（4870 亿）远远超过格力伊利这两个人尽皆知龙头企业的市值（4300 亿）之和？",
      "link": "https://www.zhihu.com/question/1942209161707381363",
      "heat": "133 万热度"
    },
    {
      "rank": "6",
      "title": "男子被外卖员撞成十级伤残，骑手撞人后说订单超时先送外卖，骑手应承担哪些责任？平台是否应承担一定责任？",
      "link": "https://www.zhihu.com/question/1941889089877049589",
      "heat": "102 万热度"
    },
    {
      "rank": "7",
      "title": "蔚来李斌回应新车定价，称「继续保持高价，很难参与市场竞争，蔚来活下去是最重要的」，如何看待他的选择？",
      "link": "https://www.zhihu.com/question/1942176837217268142",
      "heat": "100 万热度"
    },
    {
      "rank": "8",
      "title": "美国向委内瑞拉附近部署 3 艘军舰 4000 名士兵，悬赏 5000 万美元指控马杜罗涉毒，如何解读？",
      "link": "https://www.zhihu.com/question/1942250705374123427",
      "heat": "97 万热度"
    },
    {
      "rank": "9",
      "title": "「二次元」黄金卖断货，「痛金」单价被炒至 2800 元 / 克，「痛金」凭什么这么高价？如何看待这一现象？",
      "link": "https://www.zhihu.com/question/1941872397943797207",
      "heat": "96 万热度"
    },
    {
      "rank": "10",
      "title": "男子水下憋气 29 分钟刷新世界纪录，时长约是海豚 2 倍，他是如何做到的？水下憋气对身体有哪些损伤？",
      "link": "https://www.zhihu.com/question/1941798613538797298",
      "heat": "96 万热度"
    },
    {
      "rank": "11",
      "title": "为何「西葫芦炖茄子」一菜在知乎上爆火？",
      "link": "https://www.zhihu.com/question/1894520658702079678",
      "heat": "93 万热度"
    },
    {
      "rank": "12",
      "title": "中国留学生起诉美国大学索赔 1 亿美元，因校方未规范使用有毒化学品致其患癌，到底是怎么回事？能胜诉吗？",
      "link": "https://www.zhihu.com/question/1941958293267378875",
      "heat": "93 万热度"
    },
    {
      "rank": "13",
      "title": "报道称一女子淋雨十几分钟确诊脑膜炎，浑身抽搐、口吐白沫，怎么回事？淋雨真的会诱发脑膜炎吗？",
      "link": "https://www.zhihu.com/question/1941427805704381671",
      "heat": "92 万热度"
    },
    {
      "rank": "14",
      "title": "上海高一女生军训第四天倒地后死亡，病历显示死亡原因不明，可能是哪些原因导致死亡？学校该承担责任吗？",
      "link": "https://www.zhihu.com/question/1942278351382341279",
      "heat": "92 万热度"
    },
    {
      "rank": "15",
      "title": "宇宙到底是怎么做到让一个个球悬浮的？",
      "link": "https://www.zhihu.com/question/595322405",
      "heat": "91 万热度"
    },
    {
      "rank": "16",
      "title": "我国科研团队在「可燃冰」大规模利用领域实现重要突破，仅需 70℃ 低温实现零损耗转化，有何应用前景？",
      "link": "https://www.zhihu.com/question/1941821400575866076",
      "heat": "87 万热度"
    },
    {
      "rank": "17",
      "title": "女中医石铭 UFC 首秀不敌巴西选手布拉希尔，怎样评价本场比赛？",
      "link": "https://www.zhihu.com/question/1942268411041264883",
      "heat": "85 万热度"
    },
    {
      "rank": "18",
      "title": "鲍威尔称美联储对降息持开放态度，怎样解读？美联储 9 月会降息吗？",
      "link": "https://www.zhihu.com/question/1942366417686066808",
      "heat": "84 万热度"
    },
    {
      "rank": "19",
      "title": "《浪浪山小妖怪》中真齐天大圣为何要捣毁双狗洞？导演为何有意加上这个情节？",
      "link": "https://www.zhihu.com/question/1937170908583293178",
      "heat": "81 万热度"
    },
    {
      "rank": "20",
      "title": "如何评价《少女前线 2：追放》因可露凯泳装获取机制引发的玩家争议和官方的应对方案？",
      "link": "https://www.zhihu.com/question/1941196636807225583",
      "heat": "81 万热度"
    },
    {
      "rank": "21",
      "title": "演员许荔莎自曝 22 年因许凯出轨分手，许凯方回应「假消息，已报警」，具体是怎么回事？",
      "link": "https://www.zhihu.com/question/1942183164203200891",
      "heat": "80 万热度"
    },
    {
      "rank": "22",
      "title": "麦当劳鳕鱼堡（麦香鱼）用的是真鳕鱼吗？",
      "link": "https://www.zhihu.com/question/665362109",
      "heat": "79 万热度"
    },
    {
      "rank": "23",
      "title": "如何看待「李世民」扮演者郑国霖在景区打工，回应「凭能力工作，需养家糊口」？",
      "link": "https://www.zhihu.com/question/1940642966621360487",
      "heat": "77 万热度"
    },
    {
      "rank": "24",
      "title": "阳光玫瑰葡萄价格销量均锐减，是「过气」了吗？网友吐槽其「甜到发齁，没有葡萄原有香味」，可能是什么原因？",
      "link": "https://www.zhihu.com/question/1941179753546651484",
      "heat": "73 万热度"
    },
    {
      "rank": "25",
      "title": "如何评价 2025 年 8 月米哈游《绝区零》2.2 版本前瞻直播【不要温和地走入那良夜】？",
      "link": "https://www.zhihu.com/question/1941938453446109148",
      "heat": "72 万热度"
    },
    {
      "rank": "26",
      "title": "为什么拳皇 97 高手如河池等人，不学小孩，玩街霸 6，去沙特打石油杯，赚几十万美元的高额奖金？",
      "link": "https://www.zhihu.com/question/1942017164350554735",
      "heat": "70 万热度"
    },
    {
      "rank": "27",
      "title": "孩子小的时候需不需要多带孩子出去看看世界？",
      "link": "https://www.zhihu.com/question/1940328289676813397",
      "heat": "69 万热度"
    },
    {
      "rank": "28",
      "title": "警校为什么叫师兄师姐而不是学长学姐？不小心叫了学长学姐对方会不高兴吗？",
      "link": "https://www.zhihu.com/question/1940021897493455446",
      "heat": "67 万热度"
    },
    {
      "rank": "29",
      "title": "孙权为什么认为鲁肃劝借荆州是个错误？",
      "link": "https://www.zhihu.com/question/563971959",
      "heat": "66 万热度"
    },
    {
      "rank": "30",
      "title": "汉语把「火」和「箭」组成「火箭」，为什么英语不把「rocket」叫做「fire arrow」？",
      "link": "https://www.zhihu.com/question/1940839934907875725",
      "heat": "66 万热度"
    },
    {
      "rank": "31",
      "title": "家里的旧衣服太多了，穿又穿不了，想扔又舍不得，想问下大家旧衣服都是怎么处理的？",
      "link": "https://www.zhihu.com/question/511339145",
      "heat": "66 万热度"
    },
    {
      "rank": "32",
      "title": "跑高速为什么要「逢三必进」？",
      "link": "https://www.zhihu.com/question/10839577574",
      "heat": "63 万热度"
    },
    {
      "rank": "33",
      "title": "为什么英文里人称后要分为 am are is，都用一个不也能表达清楚意思么？",
      "link": "https://www.zhihu.com/question/1940343220253995311",
      "heat": "59 万热度"
    },
    {
      "rank": "34",
      "title": "如何判断一个人有真的数学研究天赋?",
      "link": "https://www.zhihu.com/question/1941469173294294482",
      "heat": "59 万热度"
    },
    {
      "rank": "35",
      "title": "ACL2025 重磅收录百度智能云两项重大技术研究成果，有哪些信息值得关注？",
      "link": "https://www.zhihu.com/question/1941994010928452478",
      "heat": "59 万热度"
    },
    {
      "rank": "36",
      "title": "以前电子设备性能有限时时，程序员们为了减少性能占用，都有过什么巧思？",
      "link": "https://www.zhihu.com/question/8715804536",
      "heat": "59 万热度"
    },
    {
      "rank": "37",
      "title": "在写小说的时候要怎么改善分镜视角切换混乱的问题呢？",
      "link": "https://www.zhihu.com/question/1927434523206984426",
      "heat": "59 万热度"
    },
    {
      "rank": "38",
      "title": "如何评价尼康发布的 24-70/2.8 S II 镜头？",
      "link": "https://www.zhihu.com/question/1942199380791791770",
      "heat": "59 万热度"
    },
    {
      "rank": "39",
      "title": "线性代数特征值到底是个什么东西？",
      "link": "https://www.zhihu.com/question/37615080",
      "heat": "59 万热度"
    },
    {
      "rank": "40",
      "title": "哪座城市的公共雕塑让你印象最深？它如何融入或挑战了城市气质？",
      "link": "https://www.zhihu.com/question/1923712784576767706",
      "heat": "59 万热度"
    },
    {
      "rank": "41",
      "title": "强者思维是怎样的？",
      "link": "https://www.zhihu.com/question/503758104",
      "heat": "59 万热度"
    },
    {
      "rank": "42",
      "title": "都说刀塔里面减 CD 的元素太少，但在刀塔这个游戏中此元素需要有很多吗？",
      "link": "https://www.zhihu.com/question/1941274562986770957",
      "heat": "59 万热度"
    },
    {
      "rank": "43",
      "title": "如何理解「不把『休息』贬低为『不上进』，才是巩固自体稳定性」？如何看待这个观点？",
      "link": "https://www.zhihu.com/question/1940129671237854289",
      "heat": "59 万热度"
    },
    {
      "rank": "44",
      "title": "为什么现在很多人 30 岁了，还觉得自己还没长大？这是种怎样的心理？",
      "link": "https://www.zhihu.com/question/1938633527387186461",
      "heat": "59 万热度"
    },
    {
      "rank": "45",
      "title": "苏超启用全省统一预约购票平台，实行预约 + 公证摇号方式，这对苏超来说是好事还是坏事？观赛人数会受影响吗？",
      "link": "https://www.zhihu.com/question/1941867510430396749",
      "heat": "58 万热度"
    },
    {
      "rank": "46",
      "title": "我明明对父母已经没了期望，为什么还会对他们感到愤怒呢？",
      "link": "https://www.zhihu.com/question/1939081014212264112",
      "heat": "58 万热度"
    },
    {
      "rank": "47",
      "title": "元末和五代十国，哪个统一天下的难度更大?",
      "link": "https://www.zhihu.com/question/1941090339264888975",
      "heat": "58 万热度"
    },
    {
      "rank": "48",
      "title": "学代码有一段时间了，有没有什么渠道可以实战的？",
      "link": "https://www.zhihu.com/question/1940345062979515867",
      "heat": "58 万热度"
    },
    {
      "rank": "49",
      "title": "有哪些鲜为人知的特色地方美食？",
      "link": "https://www.zhihu.com/question/353828402",
      "heat": "58 万热度"
    },
    {
      "rank": "50",
      "title": "韩立伪灵根结婴为什么无人注意？",
      "link": "https://www.zhihu.com/question/1940813406132245257",
      "heat": "58 万热度"
    }
  ],
  "generated_at": "2025-08-23 05:40:22"
}